comb/__init__.py
comb/__main__.py
comb/registry.py
comb/sweep.py
comb/types.py
comb/util.py
comb_py-0.0.3.dist-info/LICENSE
comb_py-0.0.3.dist-info/METADATA
comb_py-0.0.3.dist-info/WHEEL
comb_py-0.0.3.dist-info/entry_points.txt
comb_py-0.0.3.dist-info/top_level.txt
comb_py-0.0.3.dist-info/RECORD
