Metadata-Version: 2.1
Name: comb-py
Version: 0.0.3
Summary: Configure experiments
Home-page: https://github.com/stes/comb
Author: Steffen Schneider
Author-email: stes@hey.com
Project-URL: Bug Tracker, https://github.com/stes/comb/issues
Classifier: Programming Language :: Python :: 3
Classifier: Intended Audience :: Developers
Classifier: License :: OSI Approved :: MIT License
Classifier: Topic :: Software Development :: Libraries
Classifier: Topic :: Utilities
Requires-Python: >=3.7
License-File: LICENSE
